mazely/__about__.py
mazely/__init__.py
mazely/maze.py
mazely/utilities.py
mazely/algorithms/__init__.py
mazely/algorithms/maze_generator.py
mazely/algorithms/maze_solver.py
mazely/algorithms/recursive_backtracking.py
mazely/algorithms/shortest_path.py
mazely-0.2.0.dist-info/LICENSE
mazely-0.2.0.dist-info/METADATA
mazely-0.2.0.dist-info/WHEEL
mazely-0.2.0.dist-info/top_level.txt
mazely-0.2.0.dist-info/RECORD
