Metadata-Version: 2.1
Name: mazely
Version: 0.2.0
Summary: Implementation of maze-related algorithms
Author: Kenneth C.
License: MIT License
Project-URL: Documentation, https://mazely.readthedocs.io
Project-URL: Repository, https://github.com/Munckenh/mazely.git
Keywords: mazely,maze,algorithms
Classifier: Development Status :: 1 - Planning
Classifier: License :: OSI Approved :: MIT License
Classifier: Intended Audience :: Developers
Classifier: Topic :: Games/Entertainment :: Puzzle Games
Classifier: Topic :: Software Development :: Libraries
Classifier: Natural Language :: English
Classifier: Programming Language :: Python :: 3.11
Classifier: Programming Language :: Python :: 3 :: Only
Requires-Python: >=3.11
License-File: LICENSE
Requires-Dist: matplotlib (>=3.7)
Requires-Dist: numpy (>=1.25)
Provides-Extra: docs
Requires-Dist: sphinx (<8.0,>=6.0) ; extra == 'docs'
Requires-Dist: furo (==2023.5.20) ; extra == 'docs'
Provides-Extra: test
Requires-Dist: pytest (>=7.4) ; extra == 'test'
Requires-Dist: pytest-mpl (>=0.16) ; extra == 'test'
Requires-Dist: pytest-mock (>=3.11) ; extra == 'test'
Requires-Dist: cairosvg (>=2.7) ; extra == 'test'
Requires-Dist: cairocffi (==1.6.0) ; extra == 'test'
Requires-Dist: flake8 (>=6.0) ; extra == 'test'
